pythermogis/__init__.py
pythermogis/pythermogis.py
pythermogis/datamodels/__init__.py
pythermogis/datamodels/configuration.py
pythermogis/physics/__init__.py
pythermogis/physics/temperature_grid_calculation.py
pythermogis/resources/__init__.py
pythermogis/resources/thermogis_jar/__init__.py
pythermogis/statistics/__init__.py
pythermogis/statistics/calculate_pvalues.py
pythermogis/thermogis_classes/__init__.py
pythermogis/thermogis_classes/doublet.py
pythermogis/thermogis_classes/java_start.py
pythermogis/utils/__init__.py
pythermogis/utils/convert_python_to_java.py
pythermogis/utils/get_repo_root.py
pythermogis-0.1.6.dist-info/licenses/LICENSE
pythermogis-0.1.6.dist-info/METADATA
pythermogis-0.1.6.dist-info/WHEEL
pythermogis-0.1.6.dist-info/top_level.txt
pythermogis-0.1.6.dist-info/RECORD
