Metadata-Version: 2.4
Name: pythermogis
Version: 0.1.6
Summary: This is a Python API to the ThermoGIS Java code
Author-email: Brett <hen.brett@tno.nl>
License: Permission is hereby granted, free of charge, to any person obtaining a copy of this software and associated documentation files (the “Software”), to deal in the Software without restriction, including without limitation the rights to use, copy, modify, merge, publish, distribute, sublicense, and/or sell copies of the Software, and to permit persons to whom the Software is furnished to do so, subject to the following conditions:
Requires-Python: >=3.11
License-File: LICENSE
Requires-Dist: jpype1<2,>=1.5.2
Requires-Dist: xarray==2024.9.0.*
Requires-Dist: pandas<3,>=2.2.3
Requires-Dist: pytz<2025,>=2024.1
Requires-Dist: pygridsio<0.4,>=0.3.11
Dynamic: license-file
